ml_agents/__init__.py
ml_agents/config.py
ml_agents/cli/__init__.py
ml_agents/cli/config_loader.py
ml_agents/cli/display.py
ml_agents/cli/main.py
ml_agents/cli/validators.py
ml_agents/cli/commands/__init__.py
ml_agents/cli/commands/db.py
ml_agents/cli/commands/eval.py
ml_agents/cli/commands/preprocess.py
ml_agents/cli/commands/results.py
ml_agents/cli/commands/setup.py
ml_agents/core/__init__.py
ml_agents/core/benchmark_registry.py
ml_agents/core/database_manager.py
ml_agents/core/dataset_loader.py
ml_agents/core/dataset_preprocessor.py
ml_agents/core/dataset_uploader.py
ml_agents/core/experiment_runner.py
ml_agents/core/local_test_dataset.py
ml_agents/core/phase14_analysis.py
ml_agents/core/phase14_comparison.py
ml_agents/core/phase14_test_data.py
ml_agents/core/reasoning_inference.py
ml_agents/core/repository_manager.py
ml_agents/core/results_processor.py
ml_agents/reasoning/__init__.py
ml_agents/reasoning/base.py
ml_agents/reasoning/chain_of_thought.py
ml_agents/reasoning/chain_of_verification.py
ml_agents/reasoning/none.py
ml_agents/reasoning/program_of_thought.py
ml_agents/reasoning/reasoning_as_planning.py
ml_agents/reasoning/reflection.py
ml_agents/reasoning/skeleton_of_thought.py
ml_agents/reasoning/tree_of_thought.py
ml_agents/reasoning/prompts/base.txt
ml_agents/reasoning/prompts/chain_of_thought.txt
ml_agents/reasoning/prompts/chain_of_verification.txt
ml_agents/reasoning/prompts/program_of_thought.txt
ml_agents/reasoning/prompts/reasoning_as_planning.txt
ml_agents/reasoning/prompts/reflection.txt
ml_agents/reasoning/prompts/skeleton_of_thought.txt
ml_agents/reasoning/prompts/tree_of_thought.txt
ml_agents/utils/__init__.py
ml_agents/utils/answer_extraction.py
ml_agents/utils/api_clients.py
ml_agents/utils/env_validator.py
ml_agents/utils/instructor_clients.py
ml_agents/utils/logging_config.py
ml_agents/utils/output_parser.py
ml_agents/utils/rate_limiter.py
ml_agents/utils/reasoning_extraction.py
ml_agents_reasoning-0.0.20a0.dist-info/licenses/LICENSE
ml_agents_reasoning-0.0.20a0.dist-info/METADATA
ml_agents_reasoning-0.0.20a0.dist-info/WHEEL
ml_agents_reasoning-0.0.20a0.dist-info/entry_points.txt
ml_agents_reasoning-0.0.20a0.dist-info/top_level.txt
ml_agents_reasoning-0.0.20a0.dist-info/RECORD
