Metadata-Version: 2.4
Name: ml-agents-reasoning
Version: 0.0.20a0
Summary: ML Agents Reasoning Research Platform
Author-email: Matthew Thompson <thompsonson@gmail.com>
License-Expression: CC-BY-4.0
Project-URL: Homepage, https://github.com/thompsonson/c4ai-ml-agents
Project-URL: Documentation, https://github.com/thompsonson/c4ai-ml-agents#readme
Project-URL: Repository, https://github.com/thompsonson/c4ai-ml-agents
Project-URL: Issues, https://github.com/thompsonson/c4ai-ml-agents/issues
Keywords: reasoning,llm,benchmark,research,ai
Classifier: Development Status :: 4 - Beta
Classifier: Intended Audience :: Science/Research
Classifier: Topic :: Scientific/Engineering :: Artificial Intelligence
Classifier: Programming Language :: Python :: 3.9
Classifier: Programming Language :: Python :: 3.10
Classifier: Programming Language :: Python :: 3.11
Classifier: Programming Language :: Python :: 3.12
Requires-Python: >=3.9
License-File: LICENSE
Requires-Dist: numpy<2.0.0
Requires-Dist: openai>=1.3.0
Requires-Dist: cohere>=4.37.0
Requires-Dist: anthropic>=0.8.0
Requires-Dist: pandas>=2.1.0
Requires-Dist: datasets>=2.14.0
Requires-Dist: python-dotenv>=1.0.0
Requires-Dist: tqdm>=4.66.0
Requires-Dist: huggingface_hub>=0.19.0
Requires-Dist: pyyaml>=6.0.1
Requires-Dist: typer>=0.9.0
Requires-Dist: rich>=13.0.0
Requires-Dist: instructor>=1.0.0
Requires-Dist: pydantic>=2.0.0
Requires-Dist: sqlalchemy>=2.0.0
Requires-Dist: openpyxl>=3.1.5
Requires-Dist: matplotlib>=3.7.0
Requires-Dist: seaborn>=0.12.0
Provides-Extra: dev
Requires-Dist: black>=23.0.0; extra == "dev"
Requires-Dist: mypy>=1.5.0; extra == "dev"
Requires-Dist: pytest>=7.4.0; extra == "dev"
Requires-Dist: pytest-cov>=4.0.0; extra == "dev"
Requires-Dist: pytest-mock>=3.11.0; extra == "dev"
Requires-Dist: pytest-asyncio>=0.21.0; extra == "dev"
Requires-Dist: flake8>=6.0.0; extra == "dev"
Requires-Dist: isort>=5.12.0; extra == "dev"
Requires-Dist: pre-commit>=3.4.0; extra == "dev"
Requires-Dist: build>=0.10.0; extra == "dev"
Requires-Dist: twine>=4.0.0; extra == "dev"
Requires-Dist: setuptools-scm>=7.0.0; extra == "dev"
Dynamic: license-file
